parallel_transform/__init__.py
parallel_transform-0.0.2.dist-info/METADATA
parallel_transform-0.0.2.dist-info/WHEEL
parallel_transform-0.0.2.dist-info/top_level.txt
parallel_transform-0.0.2.dist-info/RECORD
