Metadata-Version: 2.1
Name: parallel-transform
Version: 0.0.2
Summary: A implementation of asynchronous multiprocessing with progress logging.
Home-page: https://github.com/sarenehan/parallel-transform
Author: Stewart Renehan
Author-email: sarenehan@gmail.com
License: UNKNOWN
Platform: UNKNOWN
Classifier: Programming Language :: Python :: 3
Classifier: License :: OSI Approved :: MIT License
Classifier: Operating System :: OS Independent
